Metadata-Version: 1.1
Name: pymania
Version: 0.1.1
Summary: MANIA anatomical inference
Home-page: https://github.com/kamalshadi/mania/
Author: Kamal Shadi
Author-email: kamal.shadi85@gmail.com
License: MIT
Download-URL: https://github.com/kamalshadi/mania/archive/0.1.tar.gz
Platform: UNKNOWN
